AUTHORS.rst
CHANGELOG.rst
LICENSE
MANIFEST.in
README.rst
setup.py
multicore/__init__.py
multicore/__init__.pyc
multicore/exceptions.py
multicore/exceptions.pyc
multicore/utils.py
multicore/utils.pyc
multicore.egg-info/PKG-INFO
multicore.egg-info/SOURCES.txt
multicore.egg-info/dependency_links.txt
multicore.egg-info/not-zip-safe
multicore.egg-info/requires.txt
multicore.egg-info/top_level.txt
multicore/__pycache__/__init__.cpython-35.pyc
multicore/__pycache__/__init__.pypy-41.pyc
multicore/__pycache__/exceptions.cpython-35.pyc
multicore/__pycache__/exceptions.pypy-41.pyc
multicore/__pycache__/utils.cpython-35.pyc
multicore/__pycache__/utils.pypy-41.pyc
multicore/tests/__init__.py
multicore/tests/__init__.pyc
multicore/tests/test_base.py
multicore/tests/test_base.pyc
multicore/tests/test_utils.py
multicore/tests/test_utils.pyc
multicore/tests/__pycache__/__init__.cpython-35.pyc
multicore/tests/__pycache__/__init__.pypy-41.pyc
multicore/tests/__pycache__/test_base.cpython-27-PYTEST.pyc
multicore/tests/__pycache__/test_base.cpython-35-PYTEST.pyc
multicore/tests/__pycache__/test_base.pypy-41-PYTEST.pyc
multicore/tests/__pycache__/test_utils.cpython-27-PYTEST.pyc
multicore/tests/__pycache__/test_utils.cpython-35-PYTEST.pyc
multicore/tests/__pycache__/test_utils.pypy-41-PYTEST.pyc