Metadata-Version: 1.1
Name: multicore
Version: 0.1.1
Summary: Simpler Python multiprocess coding. Persistent workers, memory maps for minimum overhead.
Home-page: http://github.com/praekelt/multicore
Author: Praekelt Consulting
Author-email: dev@praekelt.com
License: BSD
Platform: UNKNOWN
Classifier: Programming Language :: Python
Classifier: License :: OSI Approved :: BSD License
Classifier: Operating System :: OS Independent
Classifier: Intended Audience :: Developers
Classifier: Topic :: Internet :: WWW/HTTP :: Dynamic Content
